Workbook
Name ExternalData_1: 'Индекс с Дивидендами'!$A$1:$J$905
Name ExternalData_2: 'Все_дивиденды_xlsx'!$A$1:$C$649

Sheet Дивиденды
A1: Дивиденды эмитентов РФ с 2019 года
A3: Эмитент | B3: Тикер | C3: 2019 | D3: 2020 | E3: 2021 | F3: 2022 | G3: 2023 | H3: 2024 | I3: 2025
A4: "МОСКОВСКИЙ КРЕДИТНЫЙ БАНК" (ПАО) | B4: CBOM | C4: 0.11 | D4: - | E4: - | F4: - | G4: - | H4: - | I4: -
A5: Акционерная компания "АЛРОСА" (ПАО) | B5: ALRS | C5: 7.95 | D5: 2.63 | E5: 18.33 | F5: - | G5: 3.77 | H5: 4.51 | I5: -
A6: Банк ВТБ (ПАО) | B6: VTBR | C6: 0.00128 | D6: 0.00077 | E6: 0.0014 | I6: 25.58
A7: Международная Компания ПАО "МД Медикал Груп Инвестментс" | B7: MDMG | E7: 37 | F7: 8.55 | H7: 183 | I7: 64
A8: Международная Компания ПАО Юнайтед Медикал Груп | B8: GEMC | E8: 109.74
A9: Международная компания ПАО "ВК" | B9: VKCO | C9: - | D9: - | E9: - | F9: - | G9: - | H9: - | I9: -
A10: Международная компания ПАО "Озон" | B10: OZON | C10: - | D10: - | E10: - | F10: - | G10: - | H10: - | I10: 143.55
A11: Международная компания ПАО "Лента" | B11: LENT | C11: - | D11: - | E11: - | F11: - | G11: - | H11: - | I11: -
A12: Международная компания ПАО "Объединённая Компания "РУСАЛ"" | B12: RUAL | C12: - | D12: - | E12: - | F12: 1.21 | G12: - | H12: - | I12: -
A13: Международная компания ПАО "Т-Технологии" | B13: T | C13: 32.18 | D13: 59.86 | E13: 18.39 | H13: 92.5 | I13: 100
A14: Международная компания ПАО "Хэдхантер" | B14: HEAD | C14: 23.37 | D14: 39.15 | E14: 40.04 | F14: 54.81 | H14: 907 | I14: 233
A15: Международная компания ПАО "Циан" | B15: CNRU | C15: - | D15: - | E15: - | F15: - | G15: - | H15: - | I15: 104
A16: Международная компания ПАО "ЭН+ ГРУП" | B16: ENPG | C16: - | D16: - | E16: - | F16: - | G16: - | H16: - | I16: -
A17: Международная компания ПАО "ЯНДЕКС" | B17: YDEX | C17: - | D17: - | E17: - | F17: - | G17: - | H17: 80 | I17: 160
A18: ПАО "БАНК "САНКТ-ПЕТЕРБУРГ" | B18: BSPB | C18: 3.71 | D18: 3.33 | E18: 4.56 | F18: 11.81 | G18: 40.24 | H18: 50.63 | I18: 29.72
A19: ПАО "ИНАРКТИКА" | B19: AQUA | C19: - | D19: 5 | E19: 17 | F19: 38 | G19: 45 | H19: 50 | I19: 10
A20: ПАО "Акционерная финансовая корпорация "Система" | B20: AFKS | C20: 0.11 | D20: 0.13 | E20: 0.31 | F20: - | G20: 0.41 | H20: 0.52 | I20: -
A21: ПАО "Аэрофлот – российские авиалинии" | B21: AFLT | C21: 2.69 | D21: - | E21: - | F21: - | G21: - | H21: - | I21: 5.27
A22: ПАО "ВИ.ру" | B22: VSEH | C22: - | D22: - | E22: - | F22: - | G22: - | H22: - | I22: 1
A23: ПАО "Газпром" | B23: GAZP | C23: 16.61 | D23: 15.24 | E23: 12.55 | F23: 51.03 | G23: - | H23: - | I23: -
A24: ПАО "Горно-металлургическая компания "Норильский никель" | B24: GMKN | C24: 22.81 | D24: 11.8 | E24: 10.21 | F24: 26.89 | G24: 9.15 | H24: - | I24: -
A25: ПАО "Группа "Русагро" | B25: RAGR | C25: 37.69 | D25: 38.19 | E25: 144.1 | F25: - | G25: - | H25: - | I25: -
A26: ПАО "Группа ЛСР" | B26: LSRG | C26: 78 | D26: 50 | E26: 39 | G26: 78 | H26: 100 | I26: 78
A27: ПАО "Группа Позитив" | B27: POSI | C27: - | D27: - | E27: - | F27: 19.56 | G27: 72.61 | H27: 99.19 | I27: -
A28: ПАО "Группа Ренессанс Страхование" | B28: RENI | C28: - | D28: - | E28: - | F28: - | G28: 7.7 | H28: 5.9 | I28: 10.5
A29: ПАО "ДОМ.РФ" | B29: DOMRF | C29: - | D29: - | E29: - | F29: - | G29: - | H29: - | I29: -
A30: ПАО "ЕвроТранс" | B30: EUTR | C30: - | D30: - | E30: - | F30: - | G30: 8.88 | H30: 23.54 | I30: 31.85
A31: ПАО "Интер РАО ЕЭС" | B31: IRAO | C31: 0.17 | D31: 0.2 | E31: 0.18 | F31: 0.24 | G31: 0.28 | H31: 0.33 | I31: 0.35
A32: ПАО "Корпоративный центр ИКС 5" | B32: X5 | C32: 92.06 | D32: 184.11 | E32: 184.14 | F32: - | G32: - | H32: - | I32: 648
A33: ПАО "Лизинговая компания "Европлан" | B33: LEAS | C33: - | D33: - | E33: - | F33: - | G33: - | H33: 75 | I33: 87
A34: ПАО "М.видео" | B34: MVID | C34: 33.37 | D34: 30 | E34: 73 | F34: - | G34: - | H34: - | I34: -
A35: ПАО "МТС-Банк" | B35: MBNK | C35: - | D35: - | E35: - | F35: - | G35: - | H35: - | I35: 89.31
A36: ПАО "Магнитогорский металлургический комбинат" | B36: MAGN | C36: 166.78 | D36: 304.19 | E36: 784.99 | F36: - | G36: - | H36: 824.26 | I36: -
A37: ПАО "Мечел" | B37: MTLR | C37: - | D37: - | E37: - | F37: - | G37: - | H37: - | I37: -
A38: ПАО "Мечел" | B38: MTLRP | C38: 18.21 | D38: 3.48 | E38: 1.17 | F38: - | G38: - | H38: - | I38: -
A39: ПАО "Мобильные ТелеСистемы" | B39: MTSS | C39: 28.66 | D39: 42.75 | E39: 37.06 | F39: 33.85 | G39: 34.29 | H39: 35 | I39: 35
A40: ПАО "Московская Биржа ММВБ-РТС" | B40: MOEX | C40: 7.7 | D40: 7.93 | E40: 9.45 | G40: 4.84 | H40: 17.35 | I40: 26.11
A41: ПАО "Нефтяная компания "ЛУКОЙЛ" | B41: LKOH | C41: 347 | D41: 396 | E41: 553 | F41: 793 | G41: 885 | H41: 1012 | I41: 938
A42: ПАО "НоваБев Групп" | B42: BELU | C42: - | D42: 42 | E42: 162.76 | F42: 197.24 | G42: 930 | H42: 237.5 | I42: 45
A43: ПАО "Новолипецкий металлургический комбинат" | B43: NLMK | C43: 17.36 | D43: 21.64 | E43: 34.66 | F43: - | G43: 25.43 | H43: - | I43: -
A44: ПАО "Озон Фармацевтика" | B44: OZPH | C44: - | D44: - | E44: - | F44: - | G44: - | H44: 0.18 | I44: 0.79
A45: ПАО "ПИК-специализированный застройщик" | B45: PIKK | C45: 22.71 | D45: 22.71 | E45: 45.43 | F45: - | G45: - | H45: - | I45: -
A46: ПАО "Полюс" | B46: PLZL | C46: 306.6 | D46: 484.93 | E46: 654.63 | F46: - | G46: - | H46: 1301.75 | I46: 179.85
A47: ПАО "Ростелеком" | B47: RTKM | C47: 5 | D47: 5 | E47: 5 | F47: 4.56 | G47: 5.4465 | H47: 6.06 | I47: 2.71
A48: ПАО "Ростелеком" | B48: RTKMP | C48: 5 | D48: 5 | E48: 5 | F48: 4.56 | G48: 5.4465 | H48: 6.06 | I48: 6.25
A49: ПАО "Сбербанк России" | B49: SBER | C49: 16 | D49: 18.7 | E49: 18.7 | F49: - | G49: 25 | H49: 33.3 | I49: 34.84
A50: ПАО "Сбербанк России" | B50: SBERP | C50: 16 | D50: 18.7 | E50: 18.7 | F50: - | G50: 25 | H50: 33.3 | I50: 34.84
A51: ПАО "Северсталь" | B51: CHMF | C51: 121.7 | D51: 106.39 | E51: 253.42 | F51: - | G51: - | H51: 309.93 | I51: -
A52: ПАО "Селигдар" | B52: SELG | C52: 0.78 | D52: 3.97 | E52: 1.95 | F52: 4.5 | G52: 2 | H52: 6 | I52: -
A53: ПАО "Совкомбанк" | B53: SVCB | C53: - | D53: - | E53: - | F53: - | G53: - | H53: 1.14 | I53: 0.35
A54: ПАО "Территориальная генерирующая компания №1" | B54: TGKA | C54: 0.00064 | D54: 0.00104 | E54: 0.00107 | F54: - | G54: - | H54: - | I54: -
A55: ПАО "Транснефть" | B55: TRNFP | C55: 107.06 | D55: 116.122 | E55: 92.2428 | F55: 104.974 | G55: 166.652 | H55: 177.2 | I55: 198.25
A56: ПАО "Федеральная гидрогенерирующая компания - РусГидро" | B56: HYDR | C56: 0.03674 | D56: 0.03568 | E56: 0.05305 | F56: 0.05305 | G56: 0.05025 | H56: - | I56: -
A57: ПАО "Федеральная сетевая компания - Россети" | B57: FEES | C57: 0.01604 | D57: 0.0183 | E57: 0.01613 | F57: - | G57: - | H57: - | I57: -
A58: ПАО "Фикс Прайс" | B58: FIXR | C58: - | D58: - | E58: 11.5 | F58: - | G58: - | H58: 45.1537 | I58: -
A59: ПАО "ФосАгро" | B59: PHOR | C59: 177 | D59: 300 | E59: 558 | F59: 1098 | G59: 1020 | H59: 552 | I59: 360
A60: ПАО "ЭЛ5-Энерго" | B60: ELFV | C60: 0.14147 | D60: 0.085 | E60: - | F60: - | G60: - | H60: - | I60: -
A61: ПАО "ЭсЭфАй" | B61: SFIN | C61: 14.5 | D61: - | E61: - | F61: - | G61: 39.42 | H61: 248.2 | I61: 985.5
A62: ПАО "Юнипро" | B62: UPRO | C62: 0.22206 | D62: 0.22206 | E62: 0.31722 | F62: - | G62: - | H62: - | I62: -
A63: ПАО Группа Астра | B63: ASTR | C63: - | D63: - | E63: - | F63: - | G63: - | H63: 7.89 | I63: 5.79221
A64: ПАО Группа компаний "Сегежа" | B64: SGZH | C64: - | D64: - | E64: - | F64: 1.06 | G64: - | H64: - | I64: -
A65: ПАО Нефтегазовая компания "РуссНефть" | B65: RNFT | C65: 0.40803 | D65: - | E65: - | F65: - | G65: - | H65: - | I65: -
A66: ПАО энергетики и электрификации "Мосэнерго" | B66: MSNG | C66: 0.21004 | D66: 0.12075 | E66: 0.17945 | F66: 0.22308 | G66: 0.18652 | H66: 0.16038 | I66: -
A67: ПАО "Группа компаний "Самолет" | B67: SMLT | C67: - | D67: - | E67: 82 | F67: 82 | G67: - | H67: - | I67: -
A68: ПАО "НОВАТЭК" | B68: NVTK | C68: 31.04 | D68: 29.92 | E68: 51.41 | F68: 88.77 | G68: 95.08 | H68: 79.59 | I68: 82.15
A69: ПАО "Нефтяная компания "Роснефть" | B69: ROSN | C69: 26.67 | D69: 18.07 | E69: 24.97 | F69: 23.63 | G69: 38.36 | H69: 59.78 | I69: 51.15
A70: ПАО "Современный коммерческий флот" | B70: FLOT | C70: 0.7295 | D70: 3.6513 | E70: 6.67 | F70: - | G70: 4.29 | H70: 17.59 | I70: -
A71: ПАО "Татнефть" имени В.Д. Шашина | B71: TATN | C71: 119.11 | D71: 9.94 | E71: 28.82 | F71: 58.83 | G71: 62.11 | H71: 98.54 | I71: 74.85
A72: ПАО "Татнефть" имени В.Д. Шашина | B72: TATNP | C72: 119.11 | D72: 10.94 | E72: 28.82 | F72: 58.83 | G72: 62.11 | H72: 98.54 | I72: 74.85

Sheet Все_дивиденды_xlsx
A1: Год | B1: Ticker | C1: Dividend
A2: 2001 | B2: AFLT | C2: 0.03
A3: 2001 | B3: LKOH | C3: 8
A4: 2001 | B4: MSNG | C4: 0.007667
A5: 2001 | B5: RTKM | C5: 0.1634
A6: 2001 | B6: SBER | C6: 0.0378
A7: 2002 | B7: AFLT | C7: 0.06
A8: 2002 | B8: GMKN | C8: 23
A9: 2002 | B9: LKOH | C9: 15
A10: 2002 | B10: MSNG | C10: 0.01837
A11: 2002 | B11: RTKM | C11: 0.2144961
A12: 2002 | B12: RTKMP | C12: 0.9195237
A13: 2002 | B13: SBER | C13: 0.0525
... A648: 2025 | B648: YDEX | C648: 160

Sheet Индекс с Дивидендами
A1: Год | B1: Код инструмента | C1: Цена, RUB | D1: Эфф. кол-во | E1: Капитализация, RUB | F1: FF | G1: Wi | H1: Кап. в индексе, RUB | I1: Вес, % | J1: Dividend | K1: Див. Доходность
A2: 2025 | B2: AFKS | C2: 13.34 | D2: 1910700000 | E2: 128731000000 | F2: 0.33 | G2: 0.6 | H2: 25488738000 | I2: 0.35 | K2: ='Индекс с Дивидендами'!$J2/'Индекс с Дивидендами'!$C2 -> 0
A3: 2025 | B3: VTBR | C3: 72.25 | D3: 3310209141 | E3: 4.7832522e+11 | F3: 0.5 | G3: 1 | H3: 2.3916261e+11 | I3: 3.3 | J3: 25.58 | K3: ='Индекс с Дивидендами'!$J3/'Индекс с Дивидендами'!$C3 -> 0.35404844
A4: 2025 | B4: ALRS | C4: 41.42 | D4: 0 | E4: 3.0505688e+11 | F4: 0.34 | G4: 0.4 | H4: 4.1487735e+10 | I4: 0.57 | K4: ='Индекс с Дивидендами'!$J4/'Индекс с Дивидендами'!$C4 -> 0
A5: 2025 | B5: X5 | C5: 3011 | D5: 0 | E5: 817705917592 | F5: 0.29 | G5: 1 | H5: 2.3713472e+11 | I5: 3.27 | J5: 648 | K5: ='Индекс с Дивидендами'!$J5/'Индекс с Дивидендами'!$C5 -> 0.21521089
A6: 2025 | B6: CBOM | C6: 6.09 | D6: 0 | E6: 2.0358693e+11 | F6: 0.22 | G6: 0.7 | H6: 3.1352388e+10 | I6: 0.43 | K6: ='Индекс с Дивидендами'!$J6/'Индекс с Дивидендами'!$C6 -> 0
A7: 2025 | B7: CHMF | C7: 966.6 | D7: 0 | E7: 809738856756 | F7: 0.23 | G7: 0.4 | H7: 7.4495975e+10 | I7: 1.03 | K7: ='Индекс с Дивидендами'!$J7/'Индекс с Дивидендами'!$C7 -> 0
A8: 2025 | B8: SNGSP | C8: 41.8 | D8: 0 | E8: 321943526223 | F8: 0.73 | G8: 0.5 | H8: 1.1750939e+11 | I8: 1.62 | J8: 8.5 | K8: ='Индекс с Дивидендами'!$J8/'Индекс с Дивидендами'!$C8 -> 0.20334928
A9: 2025 | B9: DOMRF | C9: 1858.2 | D9: 0 | E9: 3.3426922e+11 | F9: 0.1 | G9: 1 | H9: 3.3426922e+10 | I9: 0.46 | K9: ='Индекс с Дивидендами'!$J9/'Индекс с Дивидендами'!$C9 -> 0
A10: 2025 | B10: ENPG | C10: 454.2 | D10: 0 | E10: 2.9016517e+11 | F10: 0.14 | G10: 0.6 | H10: 2.4373874e+10 | I10: 0.34 | K10: ='Индекс с Дивидендами'!$J10/'Индекс с Дивидендами'!$C10 -> 0
A11: 2025 | B11: FLOT | C11: 75.88 | D11: 0 | E11: 1.8021454e+11 | F11: 0.16 | G11: 0.7 | H11: 2.0184028e+10 | I11: 0.28 | K11: ='Индекс с Дивидендами'!$J11/'Индекс с Дивидендами'!$C11 -> 0
A12: 2025 | B12: GAZP | C12: 125.57 | D12: 0 | E12: 2972683014853 | F12: 0.47 | G12: 0.5 | H12: 6.9858051e+11 | I12: 9.65 | K12: ='Индекс с Дивидендами'!$J12/'Индекс с Дивидендами'!$C12 -> 0
A13: 2025 | B13: GMKN | C13: 149.02 | D13: 0 | E13: 2277970342094 | F13: 0.33 | G13: 0.4 | H13: 3.0069209e+11 | I13: 4.15 | K13: ='Индекс с Дивидендами'!$J13/'Индекс с Дивидендами'!$C13 -> 0
A14: 2025 | B14: CNRU | C14: 606.8 | D14: 0 | E14: 47130453332 | F14: 0.37 | G14: 1 | H14: 1.7438268e+10 | I14: 0.24 | J14: 104 | K14: ='Индекс с Дивидендами'!$J14/'Индекс с Дивидендами'!$C14 -> 0.1713909
A15: 2025 | B15: MTSS | C15: 213.65 | D15: 0 | E15: 4.2695422e+11 | F15: 0.41 | G15: 0.4 | H15: 7.0020493e+10 | I15: 0.97 | J15: 35 | K15: ='Индекс с Дивидендами'!$J15/'Индекс с Дивидендами'!$C15 -> 0.16381933
A16: 2025 | B16: MOEX | C16: 173.88 | D16: 0 | E16: 3.9582069e+11 | F16: 0.65 | G16: 0.3 | H16: 7.7185034e+10 | I16: 1.07 | J16: 26.11 | K16: ='Индекс с Дивидендами'!$J16/'Индекс с Дивидендами'!$C16 -> 0.15016103
A17: 2025 | B17: MAGN | C17: 28.63 | D17: 1340919600 | E17: 319921067900 | F17: 0.2 | G17: 0.6 | H17: 38390528148 | I17: 0.53 | K17: ='Индекс с Дивидендами'!$J17/'Индекс с Дивидендами'!$C17 -> 0
A18: 2025 | B18: BSPB | C18: 309 | D18: 0 | E18: 137618872989 | F18: 0.28 | G18: 0.6 | H18: 2.3119971e+10 | I18: 0.32 | J18: 46.33 | K18: ='Индекс с Дивидендами'!$J18/'Индекс с Дивидендами'!$C18 -> 0.14993528
A19: 2025 | B19: TRNFP | C19: 1381.4 | D19: 23012150 | E19: 214790432500 | F19: 0.37 | G19: 0.4 | H19: 31788984010 | I19: 0.44 | J19: 198.25 | K19: ='Индекс с Дивидендами'!$J19/'Индекс с Дивидендами'!$C19 -> 0.14351383
A20: 2025 | B20: MSNG | C20: 2.0885 | D20: 7154884746 | E20: 8.3016538e+10 | F20: 0.2 | G20: 0.9 | H20: 1.4942977e+10 | I20: 0.21 | K20: ='Индекс с Дивидендами'!$J20/'Индекс с Дивидендами'!$C20 -> 0
A21: 2025 | B21: TATNP | C21: 540.7 | D21: 103255950 | E21: 79757845950 | F21: 1 | G21: 0.7 | H21: 55830492165 | I21: 0.77 | J21: 74.85 | K21: ='Индекс с Дивидендами'!$J21/'Индекс с Дивидендами'!$C21 -> 0.13843166
A22: 2025 | B22: NLMK | C22: 106.6 | D22: 0 | E22: 638878023784 | F22: 0.21 | G22: 0.5 | H22: 6.7082192e+10 | I22: 0.93 | K22: ='Индекс с Дивидендами'!$J22/'Индекс с Дивидендами'!$C22 -> 0
A23: 2025 | B23: TATN | C23: 581 | D23: 0 | E23: 1265819296700 | F23: 0.32 | G23: 0.8 | H23: 3.2404974e+11 | I23: 4.47 | J23: 74.85 | K23: ='Индекс с Дивидендами'!$J23/'Индекс с Дивидендами'!$C23 -> 0.1288296
A24: 2025 | B24: ROSN | C24: 408.65 | D24: 0 | E24: 4.3309454e+12 | F24: 0.11 | G24: 0.4 | H24: 1.905616e+11 | I24: 2.63 | J24: 51.15 | K24: ='Индекс с Дивидендами'!$J24/'Индекс с Дивидендами'!$C24 -> 0.12516824
A25: 2025 | B25: SBERP | C25: 299.74 | D25: 557346800 | E25: 299740000000 | F25: 1 | G25: 0.5573468 | H25: 167059129832 | I25: 2.31 | J25: 34.84 | K25: ='Индекс с Дивидендами'!$J25/'Индекс с Дивидендами'!$C25 -> 0.11623407
A26: 2025 | B26: PIKK | C26: 490 | D26: 0 | E26: 323643698560 | F26: 0.21 | G26: 1 | H26: 6.7965177e+10 | I26: 0.94 | K26: ='Индекс с Дивидендами'!$J26/'Индекс с Дивидендами'!$C26 -> 0
A27: 2025 | B27: SBER | C27: 300.28 | D27: 0 | E27: 6482128745440 | F27: 0.48 | G27: 0.2786734 | H27: 8.6707049e+11 | I27: 11.97 | J27: 34.84 | K27: ='Индекс с Дивидендами'!$J27/'Индекс с Дивидендами'!$C27 -> 0.11602504
A28: 2025 | B28: POSI | C28: 997 | D28: 17091360 | E28: 71000358000 | F28: 0.24 | G28: 1 | H28: 17040085920 | I28: 0.24 | K28: ='Индекс с Дивидендами'!$J28/'Индекс с Дивидендами'!$C28 -> 0
A29: 2025 | B29: IRAO | C29: 3.1125 | D29: 23385600000 | E29: 324945000000 | F29: 0.32 | G29: 0.7 | H29: 72787680000 | I29: 1 | J29: 0.3538 | K29: ='Индекс с Дивидендами'!$J29/'Индекс с Дивидендами'!$C29 -> 0.11367068
A30: 2025 | B30: RENI | C30: 95.9 | D30: 0 | E30: 53411771602 | F30: 0.3 | G30: 0.9 | H30: 1.4421178e+10 | I30: 0.2 | J30: 10.5 | K30: ='Индекс с Дивидендами'!$J30/'Индекс с Дивидендами'!$C30 -> 0.10948905
A31: 2025 | B31: LKOH | C31: 5880.5 | D31: 0 | E31: 4074397113441 | F31: 0.55 | G31: 0.49729 | H31: 1.1143863e+12 | I31: 15.39 | J31: 541 | K31: ='Индекс с Дивидендами'!$J31/'Индекс с Дивидендами'!$C31 -> 0.09199898
A32: 2025 | B32: RUAL | C32: 33.91 | D32: 0 | E32: 5.1519513e+11 | F32: 0.18 | G32: 0.7 | H32: 6.4914587e+10 | I32: 0.9 | K32: ='Индекс с Дивидендами'!$J32/'Индекс с Дивидендами'!$C32 -> 0
A33: 2025 | B33: AFLT | C33: 57.7 | D33: 795154243 | E33: 2.29402e+11 | F33: 0.25 | G33: 0.8 | H33: 4.58804e+10 | I33: 0.63 | J33: 5.27 | K33: ='Индекс с Дивидендами'!$J33/'Индекс с Дивидендами'!$C33 -> 0.091334489
A34: 2025 | B34: HEAD | C34: 2907 | D34: 0 | E34: 137166556626 | F34: 0.42 | G34: 1 | H34: 5.7609954e+10 | I34: 0.8 | J34: 233 | K34: ='Индекс с Дивидендами'!$J34/'Индекс с Дивидендами'!$C34 -> 0.080151359
A35: 2025 | B35: PLZL | C35: 2401.6 | D35: 0 | E35: 3.2678427e+12 | F35: 0.22 | G35: 0.4 | H35: 2.8757016e+11 | I35: 3.97 | J35: 179.85 | K35: ='Индекс с Дивидендами'!$J35/'Индекс с Дивидендами'!$C35 -> 0.074887575
A36: 2025 | B36: PHOR | C36: 6371 | D36: 6734000 | E36: 825044500000 | F36: 0.26 | G36: 0.2 | H36: 42902314000 | I36: 0.59 | J36: 459 | K36: ='Индекс с Дивидендами'!$J36/'Индекс с Дивидендами'!$C36 -> 0.072045205
A37: 2025 | B37: NVTK | C37: 1188 | D37: 255049704 | E37: 3607131528000 | F37: 0.21 | G37: 0.4 | H37: 302999048352 | I37: 4.18 | J37: 82.15 | K37: ='Индекс с Дивидендами'!$J37/'Индекс с Дивидендами'!$C37 -> 0.069149832
A38: 2025 | B38: MDMG | C38: 1497.8 | D38: 0 | E38: 112522239978 | F38: 0.27 | G38: 0.9 | H38: 2.7342904e+10 | I38: 0.38 | J38: 64 | K38: ='Индекс с Дивидендами'!$J38/'Индекс с Дивидендами'!$C38 -> 0.042729336
A39: 2025 | B39: RTKM | C39: 63.99 | D39: 0 | E39: 2.1007904e+11 | F39: 0.29 | G39: 0.7 | H39: 4.2646045e+10 | I39: 0.59 | J39: 2.71 | K39: ='Индекс с Дивидендами'!$J39/'Индекс с Дивидендами'!$C39 -> 0.042350367
A40: 2025 | B40: SNGS | C40: 21.79 | D40: 0 | E40: 7.7846942e+11 | F40: 0.25 | G40: 0.7 | H40: 1.3623215e+11 | I40: 1.88 | J40: 0.9 | K40: ='Индекс с Дивидендами'!$J40/'Индекс с Дивидендами'!$C40 -> 0.04130335
A41: 2025 | B41: YDEX | C41: 4582.5 | D41: 0 | E41: 1.8022096e+12 | F41: 0.3 | G41: 1 | H41: 5.4066289e+11 | I41: 7.46 | J41: 160 | K41: ='Индекс с Дивидендами'!$J41/'Индекс с Дивидендами'!$C41 -> 0.034915439
A42: 2025 | B42: UGLD | C42: 0.5476 | D42: 0 | E42: 1.219937e+11 | F42: 0.11 | G42: 1 | H42: 1.3419307e+10 | I42: 0.19 | K42: ='Индекс с Дивидендами'!$J42/'Индекс с Дивидендами'!$C42 -> 0
A43: 2025 | B43: VKCO | C43: 302.3 | D43: 0 | E43: 173188933614 | F43: 0.2 | G43: 0.9 | H43: 3.1174008e+10 | I43: 0.43 | K43: ='Индекс с Дивидендами'!$J43/'Индекс с Дивидендами'!$C43 -> 0
A44: 2025 | B44: OZON | C44: 4495 | D44: 0 | E44: 972779729835 | F44: 0.33 | G44: 0.6 | H44: 1.9261039e+11 | I44: 2.66 | J44: 143.55 | K44: ='Индекс с Дивидендами'!$J44/'Индекс с Дивидендами'!$C44 -> 0.031935484
A45: 2025 | B45: T | C45: 3277.6 | D45: 0 | E45: 8.7929744e+11 | F45: 0.56 | G45: 0.7 | H45: 3.446846e+11 | I45: 4.76 | J45: 100 | K45: ='Индекс с Дивидендами'!$J45/'Индекс с Дивидендами'!$C45 -> 0.030510129
A46: 2025 | B46: SVCB | C46: 12.665 | D46: 0 | E46: 2.8516804e+11 | F46: 0.13 | G46: 1 | H46: 3.7071845e+10 | I46: 0.51 | J46: 0.35 | K46: ='Индекс с Дивидендами'!$J46/'Индекс с Дивидендами'!$C46 -> 0.027635215
A47: 2024 | B47: HEAD | C47: 3698 | D47: 0 | E47: 174489826764 | F47: 0.42 | G47: 1 | H47: 7.3285727e+10 | I47: 1.18 | J47: 907 | K47: ='Индекс с Дивидендами'!$J47/'Индекс с Дивидендами'!$C47 -> 0.24526771
A48: 2024 | B48: AFLT | C48: 59 | D48: 795154243 | E48: 234570501685 | F48: 0.25 | G48: 0.8 | H48: 46914100337 | I48: 0.75 | K48: ='Индекс с Дивидендами'!$J48/'Индекс с Дивидендами'!$C48 -> 0
A49: 2024 | B49: CHMF | C49: 1311 | D49: 0 | E49: 1098249163260 | F49: 0.23 | G49: 0.4 | H49: 1.0103892e+11 | I49: 1.62 | J49: 309.93 | K49: ='Индекс с Дивидендами'!$J49/'Индекс с Дивидендами'!$C49 -> 0.23640732
A50: 2024 | B50: SNGSP | C50: 60.445 | D50: 0 | E50: 4.6554728e+11 | F50: 0.73 | G50: 0.5 | H50: 1.6992476e+11 | I50: 2.73 | J50: 12.29 | K50: ='Индекс с Дивидендами'!$J50/'Индекс с Дивидендами'!$C50 -> 0.20332534
A51: 2024 | B51: FLOT | C51: 98.65 | D51: 0 | E51: 2.3429315e+11 | F51: 0.16 | G51: 0.7 | H51: 2.6240833e+10 | I51: 0.42 | J51: 17.59 | K51: ='Индекс с Дивидендами'!$J51/'Индекс с Дивидендами'!$C51 -> 0.17830715
A52: 2024 | B52: CBOM | C52: 10.15 | D52: 0 | E52: 3.3931156e+11 | F52: 0.22 | G52: 0.7 | H52: 5.2253979e+10 | I52: 0.84 | K52: ='Индекс с Дивидендами'!$J52/'Индекс с Дивидендами'!$C52 -> 0
A53: 2024 | B53: NLMK | C53: 146.42 | D53: 0 | E53: 8.7752833e+11 | F53: 0.21 | G53: 0.5 | H53: 9.2140475e+10 | I53: 1.48 | J53: 25.43 | K53: ='Индекс с Дивидендами'!$J53/'Индекс с Дивидендами'!$C53 -> 0.17367846
A54: 2024 | B54: ENPG | C54: 347.5 | D54: 0 | E54: 221999991360 | F54: 0.14 | G54: 0.6 | H54: 1.8647999e+10 | I54: 0.3 | K54: ='Индекс с Дивидендами'!$J54/'Индекс с Дивидендами'!$C54 -> 0
A55: 2024 | B55: FEES | C55: 0.07754 | D55: 0 | E55: 1.638777e+11 | F55: 0.18 | G55: 0.6 | H55: 17698791197 | I55: 0.28 | K55: ='Индекс с Дивидендами'!$J55/'Индекс с Дивидендами'!$C55 -> 0
A56: 2024 | B56: MTSS | C56: 210.3 | D56: 0 | E56: 4.2025965e+11 | F56: 0.41 | G56: 0.4 | H56: 6.8922582e+10 | I56: 1.11 | J56: 35 | K56: ='Индекс с Дивидендами'!$J56/'Индекс с Дивидендами'!$C56 -> 0.16642891
A57: 2024 | B57: GAZP | C57: 132.42 | D57: 5918378225 | E57: 3134846578218 | F57: 0.5 | G57: 0.5 | H57: 7.8371164e+11 | I57: 12.57 | K57: ='Индекс с Дивидендами'!$J57/'Индекс с Дивидендами'!$C57 -> 0
A58: 2024 | B58: GMKN | C58: 115.56 | D58: 0 | E58: 1766489415732 | F58: 0.32 | G58: 0.4 | H58: 2.2611065e+11 | I58: 3.63 | K58: ='Индекс с Дивидендами'!$J58/'Индекс с Дивидендами'!$C58 -> 0
A59: 2024 | B59: MGNT | C59: 5100 | D59: 0 | E59: 519747910500 | F59: 0.37 | G59: 0.3 | H59: 5.7692018e+10 | I59: 0.93 | J59: 824.26 | K59: ='Индекс с Дивидендами'!$J59/'Индекс с Дивидендами'!$C59 -> 0.16161961
A60: 2024 | B60: HYDR | C60: 0.5164 | D60: 0 | E60: 2.296913e+11 | F60: 0.15 | G60: 0.4 | H60: 1.3781478e+10 | I60: 0.22 | K60: ='Индекс с Дивидендами'!$J60/'Индекс с Дивидендами'!$C60 -> 0
A61: 2024 | B61: TATNP | C61: 681.5 | D61: 103255950 | E61: 100527042750 | F61: 1 | G61: 0.7 | H61: 70368929925 | I61: 1.13 | J61: 98.54 | K61: ='Индекс с Дивидендами'!$J61/'Индекс с Дивидендами'!$C61 -> 0.14459281
A62: 2024 | B62: TRNFP | C62: 1227.5 | D62: 23012150 | E62: 190860906250 | F62: 0.37 | G62: 0.4 | H62: 28247414125 | I62: 0.45 | J62: 177.2 | K62: ='Индекс с Дивидендами'!$J62/'Индекс с Дивидендами'!$C62 -> 0.14435845
A63: 2024 | B63: SELG | C63: 41.94 | D63: 257500000 | E63: 43198200000 | F63: 0.25 | G63: 1 | H63: 10799550000 | I63: 0.17 | J63: 6 | K63: ='Индекс с Дивидендами'!$J63/'Индекс с Дивидендами'!$C63 -> 0.14306152
A64: 2024 | B64: TATN | C64: 692.7 | D64: 0 | E64: 1509179047890 | F64: 0.32 | G64: 0.8 | H64: 3.8634984e+11 | I64: 6.2 | J64: 98.54 | K64: ='Индекс с Дивидендами'!$J64/'Индекс с Дивидендами'!$C64 -> 0.14225494
A65: 2024 | B65: LKOH | C65: 7240.5 | D65: 0 | E65: 5016694549761 | F65: 0.55 | G65: 0.3180602 | H65: 8.7758598e+11 | I65: 14.07 | J65: 1012 | K65: ='Индекс с Дивидендами'!$J65/'Индекс с Дивидендами'!$C65 -> 0.13976935
A66: 2024 | B66: BSPB | C66: 367 | D66: 0 | E66: 167918659377 | F66: 0.27 | G66: 0.6 | H66: 2.7202823e+10 | I66: 0.44 | J66: 50.63 | K66: ='Индекс с Дивидендами'!$J66/'Индекс с Дивидендами'!$C66 -> 0.1379564
A67: 2024 | B67: MAGN | C67: 38.535 | D67: 1340919600 | E67: 430602806550 | F67: 0.2 | G67: 0.6 | H67: 51672336786 | I67: 0.83 | J67: 5.246 | K67: ='Индекс с Дивидендами'!$J67/'Индекс с Дивидендами'!$C67 -> 0.13613598
A68: 2024 | B68: MTLR | C68: 101.46 | D68: 0 | E68: 4.223483e+10 | F68: 0.43 | G68: 0.6 | H68: 1.0896586e+10 | I68: 0.17 | K68: ='Индекс с Дивидендами'!$J68/'Индекс с Дивидендами'!$C68 -> 0
A69: 2024 | B69: MTLRP | C69: 119.8 | D69: 0 | E69: 16623078417 | F69: 0.6 | G69: 0.8 | H69: 7.9790776e+09 | I69: 0.13 | K69: ='Индекс с Дивидендами'!$J69/'Индекс с Дивидендами'!$C69 -> 0
A70: 2024 | B70: SBER | C70: 279.4 | D70: 0 | E70: 6031393271200 | F70: 0.48 | G70: 0.2869555 | H70: 8.3075591e+11 | I70: 13.32 | J70: 33.3 | K70: ='Индекс с Дивидендами'!$J70/'Индекс с Дивидендами'!$C70 -> 0.11918397
A71: 2024 | B71: SBERP | C71: 279.6 | D71: 573911000 | E71: 279600000000 | F71: 1 | G71: 0.573911 | H71: 160465515600 | I71: 2.57 | J71: 33.3 | K71: ='Индекс с Дивидендами'!$J71/'Индекс с Дивидендами'!$C71 -> 0.11909871
A72: 2024 | B72: LEAS | C72: 714.6 | D72: 15600000 | E72: 85752000000 | F72: 0.13 | G72: 1 | H72: 11147760000 | I72: 0.18 | J72: 75 | K72: ='Индекс с Дивидендами'!$J72/'Индекс с Дивидендами'!$C72 -> 0.10495382
A73: 2024 | B73: ROSN | C73: 605.6 | D73: 0 | E73: 6.4182565e+12 | F73: 0.11 | G73: 0.4 | H73: 2.8240329e+11 | I73: 4.53 | J73: 59.78 | K73: ='Индекс с Дивидендами'!$J73/'Индекс с Дивидендами'!$C73 -> 0.098712021
A74: 2024 | B74: PIKK | C74: 491.8 | D74: 0 | E74: 3.2483259e+11 | F74: 0.21 | G74: 1 | H74: 6.8214845e+10 | I74: 1.09 | K74: ='Индекс с Дивидендами'!$J74/'Индекс с Дивидендами'!$C74 -> 0
A75: 2024 | B75: PLZL | C75: =14000/50 -> 280 | D75: 0 | E75: 1904971600000 | F75: 0.22 | G75: 0.4 | H75: 167637500800 | I75: 2.69 | J75: =1301.75/50 -> 26.035 | K75: ='Индекс с Дивидендами'!$J75/'Индекс с Дивидендами'!$C75 -> 0.092982143
A76: 2024 | B76: RTKM | C76: 65.75 | D76: 0 | E76: 2.1585711e+11 | F76: 0.29 | G76: 0.7 | H76: 4.3818994e+10 | I76: 0.7 | J76: 6.06 | K76: ='Индекс с Дивидендами'!$J76/'Индекс с Дивидендами'!$C76 -> 0.0921673
A77: 2024 | B77: IRAO | C77: 3.72 | D77: 23385600000 | E77: 388368000000 | F77: 0.32 | G77: 0.7 | H77: 86994432000 | I77: 1.4 | J77: 0.326 | K77: ='Индекс с Дивидендами'!$J77/'Индекс с Дивидендами'!$C77 -> 0.087634409
A78: 2024 | B78: MOEX | C78: 198.49 | D78: 0 | E78: 4.5184293e+11 | F78: 0.64 | G78: 0.3 | H78: 8.6753842e+10 | I78: 1.39 | J78: 17.35 | K78: ='Индекс с Дивидендами'!$J78/'Индекс с Дивидендами'!$C78 -> 0.087409945
A79: 2024 | B79: RUAL | C79: 36.92 | D79: 0 | E79: 5.6092611e+11 | F79: 0.18 | G79: 0.7 | H79: 7.067669e+10 | I79: 1.13 | K79: ='Индекс с Дивидендами'!$J79/'Индекс с Дивидендами'!$C79 -> 0
A80: 2024 | B80: PHOR | C80: 6362 | D80: 6734000 | E80: 823879000000 | F80: 0.26 | G80: 0.2 | H80: 42841708000 | I80: 0.69 | J80: 552 | K80: ='Индекс с Дивидендами'!$J80/'Индекс с Дивидендами'!$C80 -> 0.086765168
A81: 2024 | B81: SVCB | C81: 14.19 | D81: 0 | E81: 2.9364709e+11 | F81: 0.1 | G81: 1 | H81: 2.9364709e+10 | I81: 0.47 | J81: 1.14 | K81: ='Индекс с Дивидендами'!$J81/'Индекс с Дивидендами'!$C81 -> 0.080338266
A82: 2024 | B82: NVTK | C82: 999.6 | D82: 255049704 | E82: 3035091477600 | F82: 0.21 | G82: 0.4 | H82: 2.5494768e+11 | I82: 4.09 | J82: 79.59 | K82: ='Индекс с Дивидендами'!$J82/'Индекс с Дивидендами'!$C82 -> 0.079621849
A83: 2024 | B83: SMLT | C83: 1031 | D83: 0 | E83: 63488318098 | F83: 0.09 | G83: 0.9 | H83: 5.1425538e+09 | I83: 0.08 | K83: ='Индекс с Дивидендами'!$J83/'Индекс с Дивидендами'!$C83 -> 0
A84: 2024 | B84: ALRS | C84: 57.6 | D84: 0 | E84: 424222020288 | F84: 0.34 | G84: 0.4 | H84: 5.7694195e+10 | I84: 0.93 | J84: 4.51 | K84: ='Индекс с Дивидендами'!$J84/'Индекс с Дивидендами'!$C84 -> 0.078298611
A85: 2024 | B85: MSNG | C85: 2.343 | D85: 7154884746 | E85: 9.313275e+10 | F85: 0.2 | G85: 0.9 | H85: 1.6763895e+10 | I85: 0.27 | J85: 0.1604 | K85: ='Индекс с Дивидендами'!$J85/'Индекс с Дивидендами'!$C85 -> 0.06845924
A86: 2024 | B86: POSI | C86: 2009.6 | D86: 15180000 | E86: 132633600000 | F86: 0.23 | G86: 1 | H86: 30505728000 | I86: 0.49 | J86: 94.63 | K86: ='Индекс с Дивидендами'!$J86/'Индекс с Дивидендами'!$C86 -> 0.047088973
A87: 2024 | B87: SNGS | C87: 24.83 | D87: 0 | E87: 8.8707645e+11 | F87: 0.25 | G87: 0.7 | H87: 1.5523838e+11 | I87: 2.49 | J87: 0.85 | K87: ='Индекс с Дивидендами'!$J87/'Индекс с Дивидендами'!$C87 -> 0.034232783
A88: 2024 | B88: AFKS | C88: 15.195 | D88: 1910700000 | E88: 146631750000 | F88: 0.33 | G88: 0.6 | H88: 29033086500 | I88: 0.47 | J88: 0.52 | K88: ='Индекс с Дивидендами'!$J88/'Индекс с Дивидендами'!$C88 -> 0.034221783
A89: 2024 | B89: T | C89: 2732 | D89: 0 | E89: 544502604144 | F89: 0.56 | G89: 0.7 | H89: 2.1344502e+11 | I89: 3.42 | J89: 92.5 | K89: ='Индекс с Дивидендами'!$J89/'Индекс с Дивидендами'!$C89 -> 0.03385798
A90: 2024 | B90: YDEX | C90: 3978 | D90: 0 | E90: 1509467196510 | F90: 0.15 | G90: 1 | H90: 2.2642008e+11 | I90: 3.63 | J90: 80 | K90: ='Индекс с Дивидендами'!$J90/'Индекс с Дивидендами'!$C90 -> 0.020110608
A91: 2024 | B91: UGLD | C91: 0.7481 | D91: 0 | E91: 1.6666086e+11 | F91: 0.1 | G91: 1 | H91: 1.6666086e+10 | I91: 0.27 | K91: ='Индекс с Дивидендами'!$J91/'Индекс с Дивидендами'!$C91 -> 0
A92: 2024 | B92: UPRO | C92: 1.824 | D92: 0 | E92: 1.1500084e+11 | F92: 0.16 | G92: 0.8 | H92: 1.4720108e+10 | I92: 0.24 | K92: ='Индекс с Дивидендами'!$J92/'Индекс с Дивидендами'!$C92 -> 0
A93: 2024 | B93: VKCO | C93: 308.2 | D93: 0 | E93: 70231056508 | F93: 0.47 | G93: 0.8 | H93: 2.6406877e+10 | I93: 0.42 | K93: ='Индекс с Дивидендами'!$J93/'Индекс с Дивидендами'!$C93 -> 0
A94: 2024 | B94: VTBR | C94: 79.71 | D94: 0 | E94: 4.2803743e+11 | F94: 0.17 | G94: 1 | H94: 7.2766363e+10 | I94: 1.17 | K94: ='Индекс с Дивидендами'!$J94/'Индекс с Дивидендами'!$C94 -> 0
A95: 2024 | B95: ASTR | C95: 472.2 | D95: 31500000 | E95: 99162000000 | F95: 0.15 | G95: 1 | H95: 14874300000 | I95: 0.24 | J95: 7.89 | K95: ='Индекс с Дивидендами'!$J95/'Индекс с Дивидендами'!$C95 -> 0.016709022
A96: 2023 | B96: PHOR | C96: 6600 | D96: 6734000 | E96: 854700000000 | F96: 0.26 | G96: 0.2 | H96: 44444400000 | I96: 0.81 | J96: 1020 | K96: ='Индекс с Дивидендами'!$J96/'Индекс с Дивидендами'!$C96 -> 0.15454545
A97: 2023 | B97: AFLT | C97: 34.93 | D97: 795154243 | E97: 1.3887369e+11 | F97: 0.25 | G97: 0.8 | H97: 2.7774738e+10 | I97: 0.51 | K97: ='Индекс с Дивидендами'!$J97/'Индекс с Дивидендами'!$C97 -> 0
A98: 2023 | B98: AGRO | C98: 1349 | D98: 0 | E98: 184363331085 | F98: 0.25 | G98: 1 | H98: 4.6090833e+10 | I98: 0.84 | K98: ='Индекс с Дивидендами'!$J98/'Индекс с Дивидендами'!$C98 -> 0
A99: 2023 | B99: MTSS | C99: 249.5 | D99: 0 | E99: 4.985962e+11 | F99: 0.41 | G99: 0.3 | H99: 6.1327333e+10 | I99: 1.12 | J99: 34.29 | K99: ='Индекс с Дивидендами'!$J99/'Индекс с Дивидендами'!$C99 -> 0.13743487
A100: 2023 | B100: CBOM | C100: 8.015 | D100: 0 | E100: 2.6793912e+11 | F100: 0.22 | G100: 0.7 | H100: 4.1262625e+10 | I100: 0.75 | K100: ='Индекс с Дивидендами'!$J100/'Индекс с Дивидендами'!$C100 -> 0
...

Sheet Лист1
A1: Год | B1: Код инструмента | C1: Цена, RUB | D1: Эфф. кол-во | E1: Капитализация, RUB | F1: FF | G1: Wi | H1: Кап. в индексе, RUB | I1: Вес, %
A2: 2025 | B2: AFKS | C2: 13.34 | D2: 1910700000 | E2: 128731000000 | F2: 0.33 | G2: 0.6 | H2: 25488738000 | I2: 0.35
A3: 2025 | B3: AFLT | C3: 57.7 | D3: 795154243 | E3: 2.29402e+11 | F3: 0.25 | G3: 0.8 | H3: 4.58804e+10 | I3: 0.63
A4: 2025 | B4: ALRS | C4: 41.42 | D4: 0 | E4: 3.0505688e+11 | F4: 0.34 | G4: 0.4 | H4: 4.1487735e+10 | I4: 0.57
A5: 2025 | B5: BSPB | C5: 309 | D5: 0 | E5: 137618872989 | F5: 0.28 | G5: 0.6 | H5: 2.3119971e+10 | I5: 0.32
A6: 2025 | B6: CBOM | C6: 6.09 | D6: 0 | E6: 2.0358693e+11 | F6: 0.22 | G6: 0.7 | H6: 3.1352388e+10 | I6: 0.43
A7: 2025 | B7: CHMF | C7: 966.6 | D7: 0 | E7: 809738856756 | F7: 0.23 | G7: 0.4 | H7: 7.4495975e+10 | I7: 1.03
A8: 2025 | B8: CNRU | C8: 606.8 | D8: 0 | E8: 47130453332 | F8: 0.37 | G8: 1 | H8: 1.7438268e+10 | I8: 0.24
A9: 2025 | B9: DOMRF | C9: 1858.2 | D9: 0 | E9: 3.3426922e+11 | F9: 0.1 | G9: 1 | H9: 3.3426922e+10 | I9: 0.46
A10: 2025 | B10: ENPG | C10: 454.2 | D10: 0 | E10: 2.9016517e+11 | F10: 0.14 | G10: 0.6 | H10: 2.4373874e+10 | I10: 0.34
A11: 2025 | B11: FLOT | C11: 75.88 | D11: 0 | E11: 1.8021454e+11 | F11: 0.16 | G11: 0.7 | H11: 2.0184028e+10 | I11: 0.28
A12: 2025 | B12: GAZP | C12: 125.57 | D12: 0 | E12: 2972683014853 | F12: 0.47 | G12: 0.5 | H12: 6.9858051e+11 | I12: 9.65
A13: 2025 | B13: GMKN | C13: 149.02 | D13: 0 | E13: 2277970342094 | F13: 0.33 | G13: 0.4 | H13: 3.0069209e+11 | I13: 4.15
... A905: 2001 | B905: YUKO | C905: 155.888 | D905: 0 | E905: 0 | F905: 0 | G905: 0 | H905: 0 | I905: 5.2
